{
	"type": "minecraft:crafting_shaped",
	"pattern": [
		"N L",
		"TGH",
		" O "
	],
	"key": {
           "N": {
			"type": "forge:ore_dict",
            "ore": "cropOnion"
		},
           "L": {
			"type": "forge:ore_dict",
            "ore": "cropLettuce"
		},
		"H": {
			"item": "xlfoodmod:cheese"
		},
		"T": {
			"type": "forge:ore_dict",
            "ore": "cropTomato"
		},
	     "G": {
			"item": "xlfoodmod:ground_beef"
		},
	     "H": {
			"item": "xlfoodmod:cheese"
		},
	     "O": {
			"item": "xlfoodmod:tortilla"
		}
	},
	"result": {
		"item": "xlfoodmod:taco"
	}
}